deepcopyall/LICENSE
deepcopyall/README.MD
deepcopyall/__init__.py
deepcopyall/requirements.txt
deepcopyall/thirdparty.json
deepcopyall-0.10.dist-info/LICENSE.rst
deepcopyall-0.10.dist-info/METADATA
deepcopyall-0.10.dist-info/WHEEL
deepcopyall-0.10.dist-info/top_level.txt
deepcopyall-0.10.dist-info/RECORD
